search_string/__init__.py
search_string/constants.py
search_string/py.typed
search_string/search_string.py
search_string/search_string_collection.py
search_string/version.py
search_string_overvaagning-0.5.3.dist-info/LICENSE
search_string_overvaagning-0.5.3.dist-info/METADATA
search_string_overvaagning-0.5.3.dist-info/WHEEL
search_string_overvaagning-0.5.3.dist-info/top_level.txt
search_string_overvaagning-0.5.3.dist-info/RECORD
