Metadata-Version: 2.2
Name: search-string-overvaagning
Version: 0.5.3
Summary: SearchString is a custom implementation for searching strings for km24.dk.
Home-page: https://github.com/kaas-mulvad/search-string
Author: Søren Mulvad
Author-email: Soeren Mulvad <shmulvad@km24.dk>
License: End-User License Agreement (EULA) of SearchString
Project-URL: Documentation, https://github.com/km24-dk/search-string/
Project-URL: Changelog, https://github.com/km24-dk/search-string/blob/main/CHANGELOG.md
Project-URL: Homepage, https://github.com/km24-dk/search-string/
Project-URL: Github, https://github.com/km24-dk/search-string
Project-URL: Source, https://github.com/km24-dk/search-string
Project-URL: Issues, https://github.com/km24-dk/search-string/issues
Classifier: License :: OSI Approved :: MIT License
Classifier: Programming Language :: Python :: 3.9
Classifier: Programming Language :: Python :: 3.10
Classifier: Programming Language :: Python :: 3.11
Classifier: Programming Language :: Python :: 3.12
Classifier: Programming Language :: Python :: 3.13
Classifier: Topic :: Software Development :: Libraries
Classifier: Typing :: Typed
Requires-Python: >=3.9.0
License-File: LICENSE
Dynamic: author
Dynamic: home-page
Dynamic: requires-python
